embedpvp/ELEmModule.py
embedpvp/__init__.py
embedpvp/get_dis.py
embedpvp/main.py
embedpvp-1.0.5.dist-info/LICENSE
embedpvp-1.0.5.dist-info/METADATA
embedpvp-1.0.5.dist-info/WHEEL
embedpvp-1.0.5.dist-info/entry_points.txt
embedpvp-1.0.5.dist-info/top_level.txt
embedpvp-1.0.5.dist-info/zip-safe
embedpvp-1.0.5.dist-info/RECORD
