Metadata-Version: 2.1
Name: embedpvp
Version: 1.0.5
Summary: EmbedPVP: Integration of Genomics and Phenotypes for Variant Prioritization using Deep Learning
Home-page: UNKNOWN
Author: Azza Althagafi
Author-email: azza.althagafi@kaust.edu.sa
License: Apache 2.0
Download-URL: https://github.com/bio-ontology-research-group/embedpvp/archive/v1.0.5.tar.gz
Platform: UNKNOWN
Requires-Python: >3.9
License-File: LICENSE
Requires-Dist: click
Requires-Dist: mowl-borg
Requires-Dist: progress
Requires-Dist: scipy ==1.7.0
